mood_img/__init__.py
mood_img/test.py
mood_img/parts/prompt.py
mood_img-0.0.1.dist-info/METADATA
mood_img-0.0.1.dist-info/WHEEL
mood_img-0.0.1.dist-info/entry_points.txt
mood_img-0.0.1.dist-info/top_level.txt
mood_img-0.0.1.dist-info/RECORD
