Metadata-Version: 2.1
Name: mood-img
Version: 0.0.1
Summary: A tool for presenting images that match the description.
Home-page: https://github.co.jp/
Author: bib_inf
Author-email: contact.bibinf@gmail.com
License: CC0 v1.0
Classifier: Programming Language :: Python :: 3
Classifier: Topic :: Software Development :: Libraries
Classifier: License :: CC0 1.0 Universal (CC0 1.0) Public Domain Dedication
Requires-Dist: ezpip
Requires-Dist: fies (>=1.5.0)
Requires-Dist: LLM00
Requires-Dist: tqdm
Requires-Dist: indent-template (>=0.0.2)
Requires-Dist: relpath (>=3.0.5)
